statstables/__init__.py
statstables/cellformatting.py
statstables/modeltables.py
statstables/parameters.py
statstables/renderers.py
statstables/tables.py
statstables/utils.py
statstables/tests/__init__.py
statstables/tests/conftest.py
statstables/tests/test_parameters.py
statstables/tests/test_tables.py
statstables-0.0.16.dist-info/licenses/LICENSE
statstables-0.0.16.dist-info/METADATA
statstables-0.0.16.dist-info/WHEEL
statstables-0.0.16.dist-info/top_level.txt
statstables-0.0.16.dist-info/RECORD
