Metadata-Version: 2.4
Name: statstables
Version: 0.0.16
Summary: A package for making custom LaTeX, HTML, and ASCII statistical tables
Author: Anderson Frailey
License:                     GNU GENERAL PUBLIC LICENSE
Project-URL: Homepage, https://github.com/andersonfrailey/statstables
Project-URL: Issues, https://github.com/andersonfrailey/statstables/issues
Keywords: statistics,tables,data,pandas,numpy,scipy,latex,html,ASCII
Classifier: Programming Language :: Python :: 3.10
Classifier: Programming Language :: Python :: 3.11
Classifier: Programming Language :: Python :: 3.12
Classifier: Programming Language :: Python :: 3.13
Classifier: Operating System :: OS Independent
Classifier: Development Status :: 2 - Pre-Alpha
Requires-Python: >=3.10
License-File: LICENSE
Requires-Dist: numpy
Requires-Dist: pandas>=2
Requires-Dist: scipy
Requires-Dist: statsmodels
Requires-Dist: linearmodels
Requires-Dist: unicodeit
Dynamic: license-file
